MANIFEST.in
README.md
requirements.txt
setup.cfg
setup.py
dcolor/__init__.py
dcolor/_dcolor.py
dcolor/attr.py
dcolor/cm.py
dcolor/color.py
dcolor/deco.py
dcolor/index.py
dcolor/mode.py
dcolor/name.py
dcolor/rgb.py
dcolor/where.py
dcolor.egg-info/PKG-INFO
dcolor.egg-info/SOURCES.txt
dcolor.egg-info/dependency_links.txt
dcolor.egg-info/not-zip-safe
dcolor.egg-info/top_level.txt